python_workspace/__init__.py
python_workspace/workspace.py
catalyst_care-0.0.1.dist-info/METADATA
catalyst_care-0.0.1.dist-info/WHEEL
catalyst_care-0.0.1.dist-info/RECORD
