Metadata-Version: 2.1
Name: catalyst-care
Version: 0.0.1
Summary: 
Author: BloodSpy
Author-email: hahaclassik@gmail.com
Requires-Python: >=3.11,<4.0
Classifier: Programming Language :: Python :: 3
Classifier: Programming Language :: Python :: 3.11
Requires-Dist: black (>=23.3.0,<24.0.0)
Requires-Dist: python-lsp-server (>=1.7.2,<2.0.0)
Requires-Dist: wemake-python-styleguide (>=0.17.0,<0.18.0)
